{
  "schemaVersion": 1,
  "id": "randombonemealflowers",
  "version": "4.5",

  "name": "Random Bone Meal Flowers",
  "description": "Randomizes the flowers spawned by bone meal, allowing all (modded) types to spawn everywhere.",
  "authors": [ "Rick South" ],
  "contact": {
    "homepage": "https://serilum.com/mod/random-bone-meal-flowers",
    "sources": "https://github.com/Serilum/Random-Bone-Meal-Flowers",
    "issues": "https://github.com/Serilum/.issue-tracker/labels/Mod:%20Random%20Bone%20Meal%20Flowers"
  },

  "license": "All Right Reserved",
  "icon": "icon.png",

  "environment": "*",
  "entrypoints": { "main": [ "com.natamus.randombonemealflowers.ModFabric" ] },

  "depends": {
    "fabricloader": ">=0.12.5",
    "fabric": "*",
    "minecraft": ">=1.20",
    "java": ">=17",
    "collective": ">=7.52"
  },

  "custom": {
    "modmenu": {
      "links": {
        "Donate <3" : "https://ricksouth.com/donate"
      }
    }
  },

  "contributors": [
	  " ",
	  "Thank you very much to my Membership sponsors for supporting the development of this mod!",
	  " ",
	  "If you would like to contribute too, check out https://serilum.com/donate.",
	  " ",
	  "Membership sponsors:",
	  " Alister",
	  " Andrean Olgo",
	  " aternosorg",
	  " BirdieMiner",
	  " Cherriesaurus",
	  " Jack",
	  " Jeremy Langford",
	  " Michael W. S.",
	  " pepe1191",
	  " Shana Gitnick",
	  " Tyler Behl"
  ]
}